CHANGES.rst
LICENSE.txt
README.rst
bootstrap.py
buildout.cfg
setup.py
js/__init__.py
js.sugar.egg-info/PKG-INFO
js.sugar.egg-info/SOURCES.txt
js.sugar.egg-info/dependency_links.txt
js.sugar.egg-info/entry_points.txt
js.sugar.egg-info/namespace_packages.txt
js.sugar.egg-info/not-zip-safe
js.sugar.egg-info/requires.txt
js.sugar.egg-info/top_level.txt
js/sugar/__init__.py
js/sugar/test_sugar.txt
js/sugar/resources/README.txt
js/sugar/resources/sugar-1.1.3.min.js