Metadata-Version: 1.0
Name: js.sugar
Version: 1.1.3
Summary: Fanstatic packaging of Sugar
Home-page: https://github.com/disko/js.sugar
Author: Andreas Kaiser
Author-email: disko@binary-punks.com
License: BSD
Platform: UNKNOWN
